AUTHORS.rst
CONTRIBUTING.rst
HISTORY.rst
LICENSE
MANIFEST.in
README.rst
setup.cfg
setup.py
djangocms_gmaps/__init__.py
djangocms_gmaps/cms_plugins.py
djangocms_gmaps/conf.py
djangocms_gmaps/forms.py
djangocms_gmaps/models.py
djangocms_gmaps/widgets.py
djangocms_gmaps.egg-info/PKG-INFO
djangocms_gmaps.egg-info/SOURCES.txt
djangocms_gmaps.egg-info/dependency_links.txt
djangocms_gmaps.egg-info/not-zip-safe
djangocms_gmaps.egg-info/requires.txt
djangocms_gmaps.egg-info/top_level.txt
djangocms_gmaps/migrations/0001_initial.py
djangocms_gmaps/migrations/0002_filer_fk_on_delete_set_null.py
djangocms_gmaps/migrations/0003_add_plugin_template_field.py
djangocms_gmaps/migrations/__init__.py
djangocms_gmaps/south_migrations/0001_initial.py
djangocms_gmaps/south_migrations/0002_auto__chg_field_location_photo__chg_field_location_marker_icon.py
djangocms_gmaps/south_migrations/0003_auto__add_field_map_plugin_template.py
djangocms_gmaps/south_migrations/__init__.py
djangocms_gmaps/static/css/djangocms_gmaps/coordinates_widget.css
djangocms_gmaps/static/js/djangocms_gmaps/coordinates_widget.js
djangocms_gmaps/static/js/djangocms_gmaps/gmaps.js
djangocms_gmaps/templates/djangocms_gmaps/default.html
djangocms_gmaps/templates/djangocms_gmaps/infowindow.html
djangocms_gmaps/templates/djangocms_gmaps/forms/coordinates_widget.html