Metadata-Version: 1.1
Name: djangocms-gmaps
Version: 0.1.5.0
Summary: The easiest way to embed Google Maps for your django-cms powered site. This is a great way to display the location of your business or event.
Home-page: https://github.com/mishbahr/djangocms-gmaps
Author: Mishbah Razzaque
Author-email: mishbahx@gmail.com
License: BSD
Keywords: djangocms-gmaps,django-cms,djangocms-googlemap,google maps,django
Platform: UNKNOWN
Classifier: Development Status :: 4 - Beta
Classifier: Framework :: Django
Classifier: Intended Audience :: Developers
Classifier: License :: OSI Approved :: BSD License
Classifier: Natural Language :: English
Classifier: Programming Language :: Python :: 2
Classifier: Programming Language :: Python :: 2.6
Classifier: Programming Language :: Python :: 2.7
Classifier: Programming Language :: Python :: 3
Classifier: Programming Language :: Python :: 3.3
